mt103.py
mt103-1.1.1.dist-info/LICENSE
mt103-1.1.1.dist-info/WHEEL
mt103-1.1.1.dist-info/METADATA
mt103-1.1.1.dist-info/RECORD
