Metadata-Version: 2.1
Name: mt103
Version: 1.1.1
Summary: Parse MT103 messages from the Swift payments network
Home-page: https://github.com/danielquinn/mt103
License: GPL-3.0-or-later
Author: Daniel Quinn
Author-email: code@danielquinn.org
Requires-Python: >=3.6,<4.0
Classifier: License :: OSI Approved :: GNU General Public License v3 (GPLv3)
Classifier: License :: OSI Approved :: GNU General Public License v3 or later (GPLv3+)
Classifier: Programming Language :: Python
Classifier: Programming Language :: Python :: 3
Classifier: Programming Language :: Python :: 3.6
Classifier: Programming Language :: Python :: 3.7
Classifier: Programming Language :: Python :: 3.8
Classifier: Programming Language :: Python :: Implementation :: CPython
Classifier: Programming Language :: Python :: Implementation :: PyPy
Classifier: Topic :: Office/Business :: Financial
Project-URL: Repository, https://github.com/danielquinn/mt103
